miwear/__init__.py
miwear/assert.py
miwear/gz.py
miwear/log.py
miwear/targz.py
miwear/unzip.py
python_miwear-0.0.7.dist-info/LICENSE
python_miwear-0.0.7.dist-info/METADATA
python_miwear-0.0.7.dist-info/WHEEL
python_miwear-0.0.7.dist-info/entry_points.txt
python_miwear-0.0.7.dist-info/top_level.txt
python_miwear-0.0.7.dist-info/RECORD
