Metadata-Version: 2.1
Name: python-miwear
Version: 0.0.7
Summary: Python Miwear tools for extracting and handling archives/logs
Home-page: https://github.com/Junbo-Zheng/python_miwear
Author: Junbo Zheng
Author-email: 3273070@qq.com
License: Apache-2.0
Platform: UNKNOWN
Classifier: Programming Language :: Python :: 3
Classifier: License :: OSI Approved :: Apache Software License
Classifier: Operating System :: OS Independent
Requires-Python: >=3.7
License-File: LICENSE
